[
  {
    "page": 1,
    "bbox": [
      94.08000183105469,
      117.99810791015625,
      419.0401306152344,
      144.16001892089844
    ],
    "text": "COGNITIVE-BEHAVIOR \nTHERAPY \nWITH NIGHTTIME \nFEARFUL \nCHILDREN"
  },
  {
    "page": 1,
    "bbox": [
      72.00001525878906,
      155.94212341308594,
      433.91961669921875,
      167.46788024902344
    ],
    "text": "THOMAS \nH. OLLENDICK, \nLOUIS \nP. HAGOPIAN \nand ROSE M. HUNTZINGER"
  },
  {
    "page": 1,
    "bbox": [
      171.83999633789062,
      171.3911590576172,
      344.2201232910156,
      180.67579650878906
    ],
    "text": "Virginia \nPolytechnic \nInstitute \nand State University"
  },
  {
    "page": 1,
    "bbox": [
      99.35995483398438,
      191.31117248535156,
      423.9000244140625,
      262.2758483886719
    ],
    "text": "Summary -In \nthis study, the nighttime \nproblems \nof two girls diagnosed \nas having separation \nanxiety \ndisorder \nwere treated \nwith cognitive-behavioral \nprocedures. \nThrough \nthe use of a \nmultiple \nbaseline \ndesign across subjects, \nthe additive \neffects of self-control \ntraining \nand self- \ncontrol \ntraining \nplus contingent \nreinforcement \nwere determined. \nFor both girls, self-report \nof \nanxiety \nand behavioral \navoidance \nof sleeping \nin their own beds was reduced \nsignificantly \nonly \nwhen to the self-control \ntraining \nthe reinforcement \ncondition \nwas added. \nResolution \nof these \nnighttime \nproblems \nalso appeared \nto generalize \nto other \nfeatures \nof separation \nanxiety \ndisorder. \nThe clinical \nand \ntheoretical \nsignificance \nof these \nfindings \nis discussed."
  },
  {
    "page": 1,
    "bbox": [
      49.919921875,
      280.982177734375,
      255.83999633789062,
      622.2680053710938
    ],
    "text": "The \nbehavioral \ntreatment \nof children’s \nfears \nhas a long and rich tradition \n(King, \nHamilton, \n& Ollendick, \n1988; \nMorris \n& Kratochwill, \n1983). In general, \nbehavioral \nprocedures \nbased \non conditioning \nparadigms \n(operant, \nrespon- \ndent, \nand vicarious) \nhave \nbeen \nshown \nto be \neffective \nin the treatment \nof children’s \nfears \nand \nphobias, \nalthough \nsuch \na conclusion \nis \nbased \nmore \non \ncase \nstudies \nthan \nwell- \ncontrolled \noutcome \nresearch \n(Ollendick, \n1986). Moreover, \npersistence \nof effects \nacross \ntime \nhas rarely \nbeen \ndemonstrated \nin these \nstudies. \nRecently, \nand \nat least \npartially \nin \nresponse \nto \nthis \nstate \nof \naffairs, \nmore \ncognitively-based \nprocedures \nhave been \nused, \nby which, \nan attempt \nis made \nto alter specific \nperceptions, \nthoughts, \nand beliefs \nthrough \nthe \ndirect manipulation \nof faulty thought \nprocesses \nand \ntheir \naccompanying \nself-statements \n(Bernard \n& Joyce, \n1984; \nEllis, \n1970). \nThe \nassumption \nhere is that maladaptive \nthinking \nleads \nto maladaptive \nbehavior. \nFrequently, \ncognitively-based \nprocedures \nare \ncombined \nwith more traditional \nbehavioral \nprocedures \nin \na multi-component \ntreatment \npackage \ncom- \nmonly \nreferred \nto \nas \ncognitive-behavior \ntherapy \n(cf., Meichenbaum, \n1977; Kendall \n& \nBraswell, \n1985). \nProbably \nthe most frequently \nused cognitive-"
  },
  {
    "page": 1,
    "bbox": [
      265.6797790527344,
      280.9822082519531,
      471.3597717285156,
      622.2680053710938
    ],
    "text": "behavioral \nprocedure \nwith \nfearful \nor phobic \nchildren \nis verbal \nself-instructional \ntraining \n(Meichenbaum, \n1977). The rationale \nfor self- \ninstructional \ntraining \nis derived \nfrom \ntwo \nmajor \nsources: \nfirst, \nEllis’ \n(1970) \nrational- \nemotive \ntherapy \nand \nits assumption \nof irra- \ntional \nself-talk \nas the \ncause \nof \nemotional \ndistress; \nand \nsecond, \nthe \ndevelopmental \nsequence \naccording \nto which children \ndevelop \ninternal \nspeech \nand \nverbal \nsymbolic \ncontrol \nover \ntheir \nbehavior \n(Luria, \n1961). \nBased \non \nLuria’s \nmodel, \nspecific \nself-statements \nare \nmodeled \nby \nthe \ntherapist \nduring \nself- \ninstructional \ntraining \nand \nsubsequently \nre- \nhearsed \nby \nthe \nchild. \nThe \nchild \nis \nthen \nrewarded \nby the therapist \nfor the expression \nof \nthese more \nappropriate \nand less fear-arousing \nself-statements. \nIn most clinical \napplications \nof \nself-control \ntraining, \ncorrespondence \nbetween \nwhat the children \nare taught \nto say to them- \nselves and what they actually \ndo in the phobic \nsituation \nis examined \nand \nconsequated. \nAs \nnoted \nearly on by Meichenbaum \n(1977, p. al), \n“There \nis a need \nfor \na cognitive-hyphen- \nbehavioral \napproach \nwhereby \nreinforcements \nfollow \nthe \nappropriate \ncorrespondence \nbetween \nsaying \nand doing. \nFocusing \non only \none side of the therapy \nequation \nis likely \nto \nprove \nless effective.”"
  },
  {
    "page": 1,
    "bbox": [
      254.3998565673828,
      638.6712646484375,
      266.2198181152344,
      647.9558715820312
    ],
    "text": "113"
  },
  {
    "page": 2,
    "bbox": [
      55.20000076293945,
      54.991127014160156,
      413.8203125,
      64.75574493408203
    ],
    "text": "I14 \nTHOMAS \nH. OLLENDICK, \nLOUIS \nP. HAGOPIAN \nand \nROSE \nM. HUNTZINGER"
  },
  {
    "page": 2,
    "bbox": [
      52.55999755859375,
      73.1420669555664,
      472.0800476074219,
      143.70787048339844
    ],
    "text": "One of the first demonstrations \nof the use of \ncolleagues \n(1979,1980, \n1982) and Richards \nand \nself-control \ntraining \nwith phobic \nchildren \nwas \nSiegel (1978) with such integrated \nself-control \nprovided \nby Richards \nand Siegel \n(1978) who \nprocedures \nare encouraging, \nit is obvious \nthat \ntreated \nSusan, \na IO-year-old \ngirl with severe \ntheir interventions \nconsisted \nof multiple \ntreat- \ndog phobia. \nAccording \nto Richards \nand Siegel \nment \ncomponents \n(relaxation \ntraining, \nself- \n(p. 316): \nmonitoring, \nverbal \nself-instructional \ntraining,"
  },
  {
    "page": 2,
    "bbox": [
      63.600006103515625,
      144.18211364746094,
      472.3198547363281,
      163.7833709716797
    ],
    "text": "(I) We modeled \nadaptive \nself-verbalization \nby talk- \nand contingency \nmanagement). \nMoreover, \nde-"
  },
  {
    "page": 2,
    "bbox": [
      63.3599853515625,
      155.94212341308594,
      469.68011474609375,
      172.03578186035156
    ],
    "text": "ing out \nloud \nand \nadministering \ntask-relevant \nin- \nmand \ncharacteristics \nassociated \nwith \nsimply"
  },
  {
    "page": 2,
    "bbox": [
      63.3599853515625,
      167.70213317871094,
      462.48016357421875,
      180.67579650878906
    ],
    "text": "structions \nto ourselves \nwhile we performed \nthe task \nbeing \nin treatment \nmay \nhave \ncompromised"
  },
  {
    "page": 2,
    "bbox": [
      63.36004638671875,
      179.46214294433594,
      471.3571472167969,
      198.43580627441406
    ],
    "text": "(e.g.. \nsaying \n‘Relax, \ntake a slow deep breath. \nI’m \ndoing fine; this dog is obviously \nfriendly; \nnotice his \ntheir \nfindings \n(Friedman \n& Ollendick, \n1989)."
  },
  {
    "page": 2,
    "bbox": [
      63.360015869140625,
      191.2221221923828,
      473.2799377441406,
      207.31581115722656
    ],
    "text": "wagging \ntail; pet him softly; nothing \nto worry about’ \nAs a result, \nfurther \nresearch \nis required \nto"
  },
  {
    "page": 2,
    "bbox": [
      63.360015869140625,
      202.9821319580078,
      472.07806396484375,
      216.19581604003906
    ],
    "text": "while \npetting \nthe dog appropriately). \ndetermine \nwhich \nof several \nvariables \nin the"
  },
  {
    "page": 2,
    "bbox": [
      63.3599853515625,
      214.7421112060547,
      468.9599304199219,
      233.71580505371094
    ],
    "text": "(2) We then asked Susan to perform \nthe task while \nwe instructed \nher aloud. \ntreatment \nprograms \naccounted \nfor the thera-"
  },
  {
    "page": 2,
    "bbox": [
      63.60003662109375,
      226.50209045410156,
      471.838134765625,
      242.5957794189453
    ],
    "text": "(3) Susan \nthen performed \nthe task and instructed \npeutic \nchanges. \nThe \nprimary \npurpose \nof the"
  },
  {
    "page": 2,
    "bbox": [
      63.36004638671875,
      238.26210021972656,
      467.0397644042969,
      251.4757843017578
    ],
    "text": "herself \nout loud. \npresent \nstudy \nwas \nto examine \nthe \nadditive"
  },
  {
    "page": 2,
    "bbox": [
      63.36004638671875,
      250.02210998535156,
      471.5981140136719,
      269.23577880859375
    ],
    "text": "(4) Susan \nthen performed \nthe task and whispered \nthe instructions \nto herself. \neffects \nof these \ntreatment \ncomponents \nin the"
  },
  {
    "page": 2,
    "bbox": [
      63.60003662109375,
      261.7821044921875,
      471.1201477050781,
      278.11578369140625
    ],
    "text": "(S) And \nfinally, \nSusan \ninteracted \nwith dogs while \ntreatment \nof nighttime \nproblems \nin two chil-"
  },
  {
    "page": 2,
    "bbox": [
      50.160003662109375,
      273.7821044921875,
      475.92010498046875,
      379.62786865234375
    ],
    "text": "using \nentirely \ncovert \nself-instructions. \ndren \ndiagnosed \nas having \nseparation \nanxiety \ndisorder. \nMore specifically, \nfollowing \nbaseline \nOf importance, \nself-control \ntraining \nin this \nassessment, \nwe implemented \na treatment \npro- \ncase study \nwas supplemented \nwith relaxation \ngram consisting \nof self-induced \nrelaxation, \nself- \ntraining, \nextensive \ncorrective \nfeedback, \nand \nmonitoring, \nand \nverbal \nself-instruction. \nprofuse \nsocial \npraise. \nA \nsimilar \ntreatment \nAlthough \nwe reinforced \nthe children \nfor using \npackage \nwas developed \nby Graziano \nand his \nthese \n“self-control” \nstrategies, \nwc \ndid \nnot \ncolleagues \nfor the treatment \nof severe \nnight- \nspecifically \nconsequate \ntheir \navoidance \nbe- \ntime \nfears \nin \n6- \nto \n12-year-old \nchildren \nhaviors. \nIn the final \nphase \nof treatment, \nWC"
  },
  {
    "page": 2,
    "bbox": [
      49.9200439453125,
      379.3821105957031,
      472.7999572753906,
      626.1078491210938
    ],
    "text": "(G raziano \n& \nMooney, \n1980; \nGraziano, \ncontinued \nthe self-control \nstrategies \nbut added \nMooney, \nHuber, \n& Ignaziak, \n1979). \nTreat- \nreinforcement \ncontingencies \nfor the successful \nment \nconsisted \nof relaxation \ntraining, \nself- \nreduction \nof \navoidance \nbehaviors. \nIn \nthis \nmonitoring \nof nighttime \nbehavior, \nand verbal \nmanner. \nwe examined \nthe additive \neffects \nof \nself-control \ntraining \n(e.g., \n“I am brave. \n1 can \ncontingent \nreinforcement \nfor the reduction \nof \ntake care of myself when I am alone. \nI can take \navoidant \nbehaviors. \ncare of myself \nwhen \n1 am in the dark”). \nThe \nchildren \nwere \nalso given \nbravery \ntokens \nfor \nhow well they performed \nthe nightly \nexercises \nand \nfor \nbeing \nbrave \nfor going \nto bed \nand \nMethod \nstaying \nin their \nbed throughout \nthe night \n(in \nspite of their fear). \nThe bravery \ntokens \ncould \nSubject5 \nbe used for a MacDonalds \nparty \nfollowing \n10 \nconsecutive \nfearless \nnights. \nA 2.5 \nto 3-year \nMary. a IO-year-old \nwhite female, \nexpressed \nfollow-up \n(Graziano \n& Mooney. \n1982) \nre- \nconcerns \nabout \nher mother’s \nwell-being \nand \nvealed \nthat \n31 of \n34 children \n(91%) \nhad \nevidenced \nnighttime \nproblems \nas she refused \nto \nmaintained \ntheir \nimprovement. \nTwo children \nsleep in her own bed. Mary began \nrequesting \nhad regressed, \nalthough \nnot back to baseline, \nthat \nshe sleep \nwith \nher mother \nabout \nthree \nwhereas \nthe \nthird \nchild \nhad \nnot \nimproved \nmonths \nprior \nto her first clinic \nappointment. \nduring \ntreatment \nor by follow-up. \nDuring \nthat \nperiod, \nmother \nallowed \nher \nto \nAlthough \nthe findings \nof Graziano \nand his \nsleep \nwith \nher intermittently \nin order \nto re-"
  },
  {
    "page": 3,
    "bbox": [
      147.60000610351562,
      52.591163635253906,
      471.179931640625,
      62.35578536987305
    ],
    "text": "Cognitive-Behavior \nTherapy \nwith Nighttime \nFearful \nChildren \n115"
  },
  {
    "page": 3,
    "bbox": [
      50.15997314453125,
      70.26212310791016,
      255.6000213623047,
      448.028076171875
    ],
    "text": "assure \nher and \nto help \nreduce \nher emerging \nfears. Ten days prior to her first appointment, \nher \nfears \nworsened \nrapidly. \nMary \nwoke \nup \nafter \nmidnight \nto the \nsound \nof sirens \nand \nbecame \nvery concerned \nthat her mother \nwas \nnot yet home \nfrom \na party \n(Mary \nwas home \nalone \nat the time). \nAfter \nthat incident, \nMary \nbegan \nsleeping \nwith her mother \nevery \nnight. \nShe \nstated \nthat \nshe \nhad \nlost \nher \ndad \n(her \nparents \ndivorced \na year \nearlier) \nand \nolder \nbrother \n(who went to college) \nand was “afraid \nof losing \nmom, \ntoo.” \nLucy, \nan eight-year-old \nwhite \nfemale, \npre- \nsented \nwith \nexcessive \nconcerns \nabout \nher \nmother’s \nwell-being, \nnighttime \nproblems \nin- \ncluding \nrefusal \nto sleep \nin her own bed, \nand \nself-disparaging \nstatements. \nThe \nconcerns \nabout \nher \nmother \nreportedly \nbegan \na few \nweeks \nbefore \nher \nmother \nhad \nback \nsurgery \n(about \nseven \nmonths \nprior \nto \nLucy’s \nfirst \nappointment). \nOver \nthe ensuing \nmonths, \nher \nconcerns \nbecame \nmore exaggerated, \nand Lucy \nbegan \nrefusing \nto sleep in her own bed, often \nsleeping \nwith \nher \nparents. \nSelf-disparaging \nstatements \nsuch as “Maybe \nI just don’t belong \non this earth” \nand “I can’t be happy \n. . . I used \nto be . . . but not now \n. . \neven \nmy friends \ndon’t \nlike me now” \nbegan \nshortly \nbefore \nher \nparents \nbrought \nher \nin \nfor \ntreatment. \nA \ndescription \nof the genesis \nof Lucy’s difficulties \nis detailed \nelsewhere \n(Ollendick \n& Huntzinger, \n1991)."
  },
  {
    "page": 3,
    "bbox": [
      51.12006378173828,
      460.482177734375,
      79.6800765991211,
      471.28216552734375
    ],
    "text": "Design"
  },
  {
    "page": 3,
    "bbox": [
      50.64007568359375,
      483.06231689453125,
      256.0799560546875,
      623.7080688476562
    ],
    "text": "A multiple \nbaseline \ndesign \nacross \nsubjects \nwas employed \nto demonstrate \nthe controlling \neffects \nof treatment \non \nnighttime \nbehaviors \n(Hersen \n& Barlow, \n1984). Following \ncomple- \ntion of a monitoring \nphase, \nduring \nwhich the \ninitial \nassessments \nwere \nconducted, \nSelf- \nControl \nTraining \n(SCT: \nrelaxation, \nself- \nmonitoring, \nand \nverbal \nself-instruction) \nwas \nimplemented. \nFollowing \nthis \nphase, \ncontin- \ngency management \nprocedures \nwere systemati- \ncally added to the program. \nFollow-up \nsessions \nwere \nconducted \nto determine \nthe \nextent \nto"
  },
  {
    "page": 3,
    "bbox": [
      266.8800354003906,
      70.0223159790039,
      470.4001159667969,
      93.54808044433594
    ],
    "text": "which treatment \neffects were maintained \nover \ntime."
  },
  {
    "page": 3,
    "bbox": [
      266.6400451660156,
      106.24217987060547,
      341.28009033203125,
      117.04217529296875
    ],
    "text": "Initial Assessment"
  },
  {
    "page": 3,
    "bbox": [
      265.9199523925781,
      129.06236267089844,
      472.0799560546875,
      623.7083129882812
    ],
    "text": "A multimodal \nassessment \nof each \nchild’s \nfearful \nbehaviors \nwas performed. \nIndividual \nproblem-focused \ninterviews \nwere \nconducted \nwith \neach \nchild \nand \nwith \nher \nparents. \nThe \ninformation \nobtained \nfrom \nthe \ninterviews \nhelped \nin deriving \na functional \nanalysis \nfrom \nthe children’s \nand their \nparents’ \nperspectives \n(see Ollendick \n& Francis, \n1988). In addition, \nthe nature, \nduration, \nfrequency, \nand intensity \nof the fears \nwere \ndetermined. \nMary expressed \nexcessive \nworries \nabout \nher \nmother’s \nwell-being \nand about \nbeing separated \nfrom her. Her concerns \nwere present \nthrough- \nout the day but were exacerbated \nat night. \nShe \nreported \nfearing \nthat something \nmight happen \nto \nher \nor \nher \nmother. \nShe \nalso \nreported \nnighttime \nfears related \nto monsters, \nburglars, \nand being \nalone \nin the dark. \nLucy’s \nprimary \nconcern \nwas \nthat \nof \nseparation \nfrom \nher \nmother \nand \nharm \nbefalling \nher \nmother \nor \nherself. \nShe reportedly \nexperienced \nphysical \ndistress \nupon \nleaving \nfor school, \nwas reluctant \nto stay with friends, \nand refused \nto sleep alone. \nNighttime \nfears \nwere \nalso \nevident \nas \nshe \nexpressed \nfear of “zombies” \nkilling \nher and of \nbeing \n“scared \nto death” \nto be alone \nat night. \nDiagnostic \ninterviews \nwere \nconducted \nseparately \nwith each child and her mother. \nThe \nChild \nAssessment \nSchedule \n(CAS; \nHodges, \n1985) was administered \nto both Mary and her \nmother. \nLucy \nand \nher \nmother \nwere \neach \nadministered \nthe child and parent \nforms of the \nAnxiety \nDisorders \nInterview \nSchedule \n(ADIS; \nSilverman \n& Nells, 1988). Both Lucy and Mary \nmet \nthe \nDiagnostic \nand \nStatistical \nManual \n(DSM-III-R; \nAmerican \nPsychiatric \nAssocia- \ntion, \n1987) criteria \nfor separation \nanxiety \ndis- \norder \n(SAD). \nLucy also met criteria \nfor Major \nDepression. \nPsychometric \nassessments \nwere \nconducted \nusing \nself- and other-report \ninstruments. \nThe \nFear \nSurvey \nSchedule \nfor \nChildren-Revised"
  },
  {
    "page": 4,
    "bbox": [
      53.279998779296875,
      54.11797332763672,
      409.4945373535156,
      63.79572677612305
    ],
    "text": "I If1 \n‘I-ffOMAS \nH. OLLENDICK. \nLOUIS \nP. HAGOPIAN \nand \nROSE \nM. \nHIlNT%INGER"
  },
  {
    "page": 4,
    "bbox": [
      50.159942626953125,
      70.9820327758789,
      256.6175537109375,
      354.6679382324219
    ],
    "text": "(FSSC-R; \nOllendick. \n19X3), the Revised \nChil- \ndren’s \nManifest \nAnxiety \nScale \n(RCMAS; \nReynolds \n& Richmond, \n197X), the State-Trait \nAnxiety \nInventory \nfor Children \n(STAIC; \nSpiel- \nberger, \n1973), and the Children’s \nDepression \nInventory \n(CDI; \nKovacs, \nlY78) were admini- \nstered \nto \neach \nchild \n(see \nTable \n1). Their \nmothers \ncompleted \nthe \nRevised \nBehavior \nProblem \nChecklist \n(RBPC; \nQuay \n& Peterson, \nlY83). A detailed \ndescription \nof these \ninstru- \nments \ncan be found \nelsewhere \n(Ollendick \n& \nFrancis, \n19X8). In addition, \nthe State Form of \nthe STAIC \nwas administered \nto each child at \nthe beginning \nof each session \nusing the follow- \ning instructions: \n“Pretend \nyou are going to go \nto sleep in your own bed. How do you feel‘?” \nBased \non the \ninitial \nassessment \ndata, \nthe \nobserved \nrelationship \nbetween \nthe nighttime \nproblems \nand \nanxieties \nregarding \nseparation \nfrom their \nmothers, \nand our previous \nexperi- \nence \nwith \nanxious \nchildren, \nwe targeted \nthe \nnighttime \nbehaviors \nof \nboth \nchildren \nfor \nchange. \nWe \nhave \nobserved \nthat \nchange \nin \nnighttime \nfears is often related \nto resolution \nof"
  },
  {
    "page": 4,
    "bbox": [
      265.9199523925781,
      71.2221450805664,
      471.5998840332031,
      130.02793884277344
    ],
    "text": "other \nseparation \nconcerns \n(cf. \nOllendick \n6i \nHuntzinger, \n1991). \nTreatment \nwas \ninitiated \nafter \nthese \nmeasures \nwere \ncompleted \nand \n2 \nweeks \nof monitoring \nwere obtained \nfor Mary \nand 4 weeks \nof monitoring \nfor Lucy."
  },
  {
    "page": 4,
    "bbox": [
      266.6399230957031,
      154.62196350097656,
      343.4815368652344,
      165.56739807128906
    ],
    "text": "Monitoring \nPhase"
  },
  {
    "page": 4,
    "bbox": [
      266.1598815917969,
      177.78221130371094,
      473.2798767089844,
      354.9080505371094
    ],
    "text": "During \nthe monitoring \nphase \nand through- \nout \ntreatment, \nLucy \nand \nMary \nrecorded \nwhether \nthey: \n(1) \nwent \nto \nbed \nwithin \n15 \nminutes \nafter \nbeing \ntold, \n(2) \nwent \nto bed \nwithout \ncomplaining, \narguing. \nor crying, \n(3) \nslept \nin their \nown \nbed with \nlights \nand \nnoise \nturned \noff, \nand \n(4) slept \nin their \nown \nbed \nthroughout \nthe night. \nAnxious \nthoughts, \nbe- \nhaviors, \nand the responses \nof others \nto their \nnighttime \nproblems \nwere \nalso recorded. \nEach of the children’s \nmothers \nrecorded \nthe \nfollowing: \n(1) the \namount \nof time \nbetween \nbeing told to go to bed and getting \nin bed, (2) \navoidance \nbehaviors, \nand \n(3) whether \ntheir \nchild slept through \nthe night in their own bed."
  },
  {
    "page": 4,
    "bbox": [
      117.5999755859375,
      402.11822509765625,
      146.17481994628906,
      411.6812744140625
    ],
    "text": "Table I"
  },
  {
    "page": 4,
    "bbox": [
      240.719970703125,
      440.9113464355469,
      358.6199951171875,
      459.79595947265625
    ],
    "text": "Phases \nof Assessment \nMary \nLucy"
  },
  {
    "page": 4,
    "bbox": [
      208.31997680664062,
      467.3113098144531,
      386.9403381347656,
      477.31597900390625
    ],
    "text": "Pre \nPost \nTwo-Year \nPre \nPost \nOne-Year"
  },
  {
    "page": 4,
    "bbox": [
      118.08000183105469,
      489.8713073730469,
      245.82003784179688,
      560.595947265625
    ],
    "text": "Child \nSelf-Report \nRCMAS \n17 \n3 \nFSSC-R: \nTotal \n153 \n144 \nFSSC-R: \n“A Lot” \n17 \n17 \nSTAIC \n(Trait \nForm) \n41 \n- \nCD1 \n7 \n0 \nParent-Report \nRBPC: \nA/W \nY \n3"
  },
  {
    "page": 4,
    "bbox": [
      269.0400390625,
      497.79132080078125,
      385.26019287109375,
      542.595947265625
    ],
    "text": "10 \n18 \nx \nIO \n148 \n168 \n134 \n136 \nI6 \n26 \nII \nIO \n33 \n49 \n37 \n36 \n2 \n16 \n9 \n‘1"
  },
  {
    "page": 4,
    "bbox": [
      276.2401123046875,
      550.351318359375,
      382.6201477050781,
      559.8759155273438
    ],
    "text": "4 \n1s \nx \nJ"
  },
  {
    "page": 4,
    "bbox": [
      118.56008911132812,
      572.6713256835938,
      400.1401062011719,
      626.5035400390625
    ],
    "text": "Note: \nRCMAS \n= Revised \nChildren’s \nManifest \nAnxiety \nScale, \nNormative \n.Y = \n12.5; FSSC-R \n= Fear \nSurvey \nSchedule \nfor Children-Revised, \nNormative \nx = \n142; FSSC-R: \n“A Lot” = Items endorsed \nas “A Lot,” Normative \n.x = 13; STAIC \n= State-Trait \nAnxiety \nInventory \nfor Children, \nNormative \nI = 3X; CD1 \n= \nChildren’s \nDepression \nInventory, \nNormative \nx = ‘9; and RBPC: \nA/W = Revised \nBehavior \nProblem \nChecklist: \nAnxiety/Withdrawal \nFactor. \nNormative \n3 = I."
  },
  {
    "page": 5,
    "bbox": [
      147.36000061035156,
      51.391151428222656,
      468.2999267578125,
      60.9157829284668
    ],
    "text": "Cognitive-Behavior \nTherapy \nwith Nighttime \nFearful \nChildren \n117"
  },
  {
    "page": 5,
    "bbox": [
      50.879974365234375,
      67.62210845947266,
      465.6002197265625,
      91.86784362792969
    ],
    "text": "A subjective \nrating \nof their child’s willingness \navoidance \nbehaviors), \nhowever, \nwas not imple- \nto go to bed was made using a lO-point \nscale. \nmented \nuntil \nthe next \nphase."
  },
  {
    "page": 5,
    "bbox": [
      49.91998291015625,
      117.28197479248047,
      432.00286865234375,
      128.80194091796875
    ],
    "text": "Self-Control Phuse \nSelf-Control Plus Reinforcement \nPhuse"
  },
  {
    "page": 5,
    "bbox": [
      50.16001892089844,
      140.58213806152344,
      255.11997985839844,
      458.5880432128906
    ],
    "text": "Based \non \nthe \nprocedures \ndescribed \nby \nGraziano \nand \nMooney \n(1980, \n1982), \nSCT \nconsisted \nof discussion \nof the development \nand \nnature \nof anxiety, \ndeep \nbreathing \nrelaxation, \ndiscussion \nof negative \nself-talk \nand instruction \nin the use of positive \nself-statements, \nproblem- \nsolving training, \nself-reinforcement \nand praise. \nBoth Mary and Lucy received \nthis treatment. \nFour \nself-instructional \nsteps \nworded \nin ques- \ntion \nform \nwere \nused: \nproblem \ndefinition \n- \n‘cWhat’s my problem?“; \nfocused \nattention \nand \nresponse \nguidance \n- \n.‘What \ncan I do about \nit’?“; self-evaluation \nand \nerror \ncorrection \n- \n“How’s \nmy \nplan \nworking?“; \nand \nself- \nreinforcement \n- \n“How \ndid I do?” \nAfter the use of these questions \nwas overtly \nmodeled \nby the therapist \nand imitated \nby the \nchild using the game “20 Questions”, \nthey were \napplied \nto the targeted \nsituation \n(i.e., sleeping \nin own bed). The therapist \novertly \nmodeled \nthe \nself-instructional \nquestions \nand demonstrated \nhow they could serve as prompts \nto engage \nin \ndeep \nbreathing \nrelaxation \nand \npositive \nself- \nstatements. \nA “coping \nmodel” \nwas enacted \nwhereby \nthe therapist \nacknowledged \nanxiety \nand continued \nto employ \nthe strategies \neven \nthough \nthey \nwere \nnot initially \neffective."
  },
  {
    "page": 5,
    "bbox": [
      265.6800842285156,
      140.10227966308594,
      470.1599426269531,
      340.7481384277344
    ],
    "text": "Following \na brief overview \nof how behaviors \nare \nlearned \nand \nmaintained, \nthe \ntherapist \nprovided \nthe mothers \nwith a specific \ndescrip- \ntion of this process \nas it related \nto their child’s \nnighttime \nbehaviors. \nThe target \nbehaviors \nof \nsleeping \nin their \nown \nbeds \nwere \nreaffirmed, \ncontinued \nhome \nmonitoring \nwas stressed, \nand \nthe principles \nof rewarding \nand ignoring \nwere \ndiscussed \nin detail. \nRole \nplays \nand \ndidactic \ninstruction \nwere used to train \nthe mothers \nto \nmake firm commands \nfor their children \nto go to \ntheir \nown \nbed; \nignore \nwhining, \ncrying, \nand \nsimilar \nbehaviors; \nignore \ntheir children \nif they \ninsisted \non \ngetting \nin bed \nwith \nthem; \nand \nprovide \nrewards \nthe morning \nafter their \nchil- \ndren slept alone \nin their own beds throughout \nthe night."
  },
  {
    "page": 5,
    "bbox": [
      50.87995910644531,
      459.0623779296875,
      255.83998107910156,
      623.4681396484375
    ],
    "text": "Initially, \nboth \ngirls practiced \ntalking \naloud \nwith the therapist \nprompting \nand then praising. \nThe overt \npractice \nand external \nguidance \nwas \nfaded until the girls were whispering \nand finally \nengaging \nin the \nstrategies \ncovertly. \nParents \nwere also trained \nin the use of these strategies \nto assist \ntheir \nchildren \nin practicing \nand \nin \ndealing \nwith their \nactual \nnighttime \nproblems. \nMary and Lucy each received \nsix individual \n50- \nminute \nweekly \nsessions \nof SCT. The girls were \nverbally \npraised \nfor the use of these strategies \nboth \nin the sessions \nby the therapist \nand \nat \nhome \nby \nthe \nparents. \nReinforcement \nfor \nactually \nstaying \nin their \nown beds \n(i.e., \ntheir"
  },
  {
    "page": 5,
    "bbox": [
      266.15985107421875,
      340.98236083984375,
      470.8797607421875,
      623.4681396484375
    ],
    "text": "Both \nMary \nand \nLucy \nwere \nconsulted \non \nthese changes \nin their treatment \nprogram, \nand \neach \nhelped \ndesign \nand \nimplement \nher own \nindividualized \nprogram. \nFor Mary, a graduated \ncriterion \napproach \nwas \ntaken, \nwhereby \nthe \nnumber \nof nights slept in her own bed per week \nwas increased \nuntil she was able to sleep in her \nown \nbed \nevery \nnight. \nFor \nLucy, \na more \nimmediate \napproach \nwas taken. \nShe was cn- \ncouraged \nto sleep in her own bed as often \nas \npossible \nfrom \nthe onset. \nReinforcements \nfor \nboth girls included \nearrings, \nvideo movie \nren- \ntals, \ntrips \nto the shopping \nmall, \nspecial \ntime \nwith mom, \nand verbal \npraise. \nAlthough \nthe continued \nuse of SCT strate- \ngies was monitored \nand encouraged \nduring \nthis \nphase, \nthe focus of treatment \nwas switched \nto \nreinforcement \nfor \nactually \nsleeping \nin their \nown \nbeds. \nWith \nLucy, \neight \n3&50-minute \nweekly \nsessions \nof SCT \nplus \nreinforcement \nwere \nsufficient, \nwhile \nMary \nrequired \ntwelve \n3&50-minute \nweekly \nsessions. \nFor both girls, \nthe \nfinal \nsession \nwas conducted \none \nmonth \nafter \nweekly \nsessions \nhad \nbeen \nterminated."
  },
  {
    "page": 6,
    "bbox": [
      50.0,
      55.519981384277344,
      411.2551574707031,
      64.39566040039062
    ],
    "text": "11x \nTHOMAS \nH. OLLENDICK. \nLOUIS \nP. HAGOPIAN \nand ROSE \nM. \n11UN’I‘ZINGEK"
  },
  {
    "page": 6,
    "bbox": [
      47.60003662109375,
      72.1020278930664,
      252.56008911132812,
      118.90782165527344
    ],
    "text": "This \nlast session \nwas used \nto reinforce \nand \nmaintain \ntreatment \ngains. \nPost-treatment \nassessment \nwas obtained \nimmediately \nfollow- \ning that \nsession."
  },
  {
    "page": 6,
    "bbox": [
      47.60002136230469,
      144.79832458496094,
      87.17572021484375,
      153.67665100097656
    ],
    "text": "Follow-up"
  },
  {
    "page": 6,
    "bbox": [
      47.12001037597656,
      166.18211364746094,
      251.84007263183594,
      236.7478485107422
    ],
    "text": "Follow-up \nsessions \nwere conducted \n2 years \nafter the final treatment \nsession \nfor Mary and \nand one year after the final treatment \nsession \nfor \nLucy. \nThe \nsame \nassessment \ninstruments \nadministered \nat \npre-treatment \nand \npost- \ntreatment \nwere \ncompleted \nat follow-up."
  },
  {
    "page": 6,
    "bbox": [
      138.0800018310547,
      291.0032043457031,
      218.7749786376953,
      299.5956726074219
    ],
    "text": "Monitoring \nSelf-control"
  },
  {
    "page": 6,
    "bbox": [
      107.12000274658203,
      299.1632080078125,
      218.53488159179688,
      307.75567626953125
    ],
    "text": "72 \n7 \ntraining (XT)"
  },
  {
    "page": 6,
    "bbox": [
      107.1199951171875,
      312.8432312011719,
      139.3347625732422,
      321.6756896972656
    ],
    "text": "x \n6"
  },
  {
    "page": 6,
    "bbox": [
      108.55998992919922,
      323.1632385253906,
      139.09475708007812,
      331.9956970214844
    ],
    "text": "$Z \n5"
  },
  {
    "page": 6,
    "bbox": [
      107.3599853515625,
      333.7232360839844,
      138.13473510742188,
      342.5556945800781
    ],
    "text": ".SL \n“$ \n:"
  },
  {
    "page": 6,
    "bbox": [
      107.11998748779297,
      347.64324951171875,
      139.81475830078125,
      372.55572509765625
    ],
    "text": "2% \n* 1 \n.F \n0 \nz"
  },
  {
    "page": 6,
    "bbox": [
      134.72000122070312,
      286.0976257324219,
      274.9769287109375,
      465.67572021484375
    ],
    "text": "1 2 \n3,4 \n5 \n6 \n7 \nE \n‘\\ \\ \n7!- \n!"
  },
  {
    "page": 6,
    "bbox": [
      228.32000732421875,
      357.42803955078125,
      239.0940704345703,
      362.044677734375
    ],
    "text": "1 \n,"
  },
  {
    "page": 6,
    "bbox": [
      228.32000732421875,
      354.67041015625,
      271.1639099121094,
      461.0849609375
    ],
    "text": "I,! \nI"
  },
  {
    "page": 6,
    "bbox": [
      228.32000732421875,
      415.02801513671875,
      231.17405700683594,
      419.6446533203125
    ],
    "text": "1"
  },
  {
    "page": 6,
    "bbox": [
      228.32000732421875,
      436.9820251464844,
      239.8011474609375,
      443.906982421875
    ],
    "text": "I \n!"
  },
  {
    "page": 6,
    "bbox": [
      352.6400146484375,
      70.9020767211914,
      379.7596740722656,
      82.42784118652344
    ],
    "text": "Results"
  },
  {
    "page": 6,
    "bbox": [
      265.52001953125,
      96.79833221435547,
      343.2559509277344,
      105.67665100097656
    ],
    "text": "Monitoring \nPhase"
  },
  {
    "page": 6,
    "bbox": [
      265.0400085449219,
      118.1821060180664,
      473.60003662109375,
      235.78794860839844
    ],
    "text": "Mary did not sleep in her bed at all during \nthe 2-week \nbaseline \nperiod, \nand \nher mother \nreported \nthat she had not done \nso for the 10 \nnights \nprior \nto coming \nin for treatment. \nThe \nfirst \nof \nMary’s \nSTAIC \n(State) \nscores \nwas \nelevated, \nwhile the second \nwas not. Lucy slept \nin her own bed a total of only two nights during \nthe four weeks \nof extended \nbaseline \nmonitor- \ning. \nHer weekly \nSTAIC \nscores \nwere consist- \nently \nhigh \n(see \nFigure \n1)."
  },
  {
    "page": 6,
    "bbox": [
      256.4000244140625,
      290.2833251953125,
      397.094970703125,
      299.11578369140625
    ],
    "text": "SCT plus reinforcement \nFollow-up"
  },
  {
    "page": 6,
    "bbox": [
      291.20001220703125,
      300.87213134765625,
      350.9618835449219,
      332.42352294921875
    ],
    "text": "/ .-.-. \n/* \n/-•"
  },
  {
    "page": 6,
    "bbox": [
      262.4000244140625,
      329.60015869140625,
      287.6288146972656,
      349.4635314941406
    ],
    "text": "/ .’ .’"
  },
  {
    "page": 6,
    "bbox": [
      237.92002868652344,
      348.2481689453125,
      360.0540466308594,
      362.7575988769531
    ],
    "text": "i-0 .0i \n1 \n1 \n1 \n1 \n1 \n1 \n1 \n1 \n1"
  },
  {
    "page": 6,
    "bbox": [
      237.92001342773438,
      364.92340087890625,
      363.4947814941406,
      373.755859375
    ],
    "text": "3 10 11 12 13 14 15 16 17 16 19 20"
  },
  {
    "page": 6,
    "bbox": [
      237.91998291015625,
      409.8321838378906,
      300.0813903808594,
      421.70355224609375
    ],
    "text": ".-.-.- \n.,*,.-.-.,."
  },
  {
    "page": 6,
    "bbox": [
      237.91998291015625,
      425.1921691894531,
      348.2671813964844,
      437.06353759765625
    ],
    "text": "1 I I 1 1 1 1 1 . * \nI \n.-.-.-."
  },
  {
    "page": 6,
    "bbox": [
      372.3199768066406,
      353.67218017578125,
      409.75982666015625,
      373.2758483886719
    ],
    "text": "L \nMary \n!yr"
  },
  {
    "page": 6,
    "bbox": [
      193.75999450683594,
      435.723388671875,
      380.774658203125,
      493.1426696777344
    ],
    "text": "3,lO \n11 12 13 14 15 16 17 16 19 20 \n2yr \nx,;;‘.~-~ ]"
  },
  {
    "page": 6,
    "bbox": [
      193.75999450683594,
      516.1233520507812,
      356.5348205566406,
      533.3035888671875
    ],
    "text": "5 6 \n7 \n6 \n9 10,ll \n12 13 14 15 16 17 181 lyr \nI \nI"
  },
  {
    "page": 6,
    "bbox": [
      193.99996948242188,
      541.8321533203125,
      245.56105041503906,
      559.1071166992188
    ],
    "text": "%-. \n\\ 0-9 \n4."
  },
  {
    "page": 6,
    "bbox": [
      149.35995483398438,
      587.4033813476562,
      357.0148010253906,
      596.4758911132812
    ],
    "text": "1 2 \n3 \n4 \n5 6 \n7 \n6 \n9 10 11 12 13 14 15 16 17 16 \nlyr"
  },
  {
    "page": 6,
    "bbox": [
      239.35995483398438,
      599.3181762695312,
      269.8547058105469,
      608.8812255859375
    ],
    "text": "Sessions"
  },
  {
    "page": 6,
    "bbox": [
      192.55995178222656,
      611.9121704101562,
      325.0946960449219,
      623.7835693359375
    ],
    "text": "Figure I. Multiple \nbaseline \nanalysis."
  },
  {
    "page": 7,
    "bbox": [
      146.39999389648438,
      51.47801971435547,
      465.3750305175781,
      61.595672607421875
    ],
    "text": "Cognitive-Behavior \nTherapy \nwith Nighttime \nFearful \nChildren \nII’)"
  },
  {
    "page": 7,
    "bbox": [
      49.44000244140625,
      70.24193572998047,
      129.84288024902344,
      81.04193115234375
    ],
    "text": "Self-Control Phase"
  },
  {
    "page": 7,
    "bbox": [
      49.679962158203125,
      93.0621109008789,
      254.40008544921875,
      210.90794372558594
    ],
    "text": "Mary \ndid not sleep \nin her own bed at all \nduring \nthe \n6 weeks \nof SCT. \nHowever, \nher \nSTAIC \n(State) \nscores remained \nlow despite \nthe \nlack \nof behavioral \nchange \n(see \nFigure \n1). \nRelative \nto the monitoring \nalone \nphase, \nLucy \nshowed \nsome slight improvement \nduring \nSCT \ntreatment; \nyet she did not sleep \nin her bed \nmore than two or three \nnights \nper week. \nHer \nSTAIC \n(State) \nscores \nalso showed \nsome \nim- \nprovement, \nalthough \nthey remained \nelevated."
  },
  {
    "page": 7,
    "bbox": [
      50.160003662109375,
      223.6020050048828,
      223.9204864501953,
      246.16201782226562
    ],
    "text": "Self-Control Training Plus Reinforcement \nPhase"
  },
  {
    "page": 7,
    "bbox": [
      50.15998840332031,
      258.1821594238281,
      255.1199188232422,
      435.0679931640625
    ],
    "text": "Mary showed \nsteady improvement \nwhen the \ncriterion-based \nreinforcement \nprogram \nwas \nadded to the SCT protocol. \nFor the most part, \nshe was able to increase \nthe number \nof nights \nin her bed one night per week and was sleeping \nin her bed every night after the ninth \nsession. \nSTAIC \n(State) \nscores remained \nat a low level \nthroughout \ntreatment. \nLucy \nshowed \na more \nrapid rate of improvement \nonce the reinforce- \nment program \nwas added. \nShe was sleeping \nin \nher bed \nevery \nnight \nwithin \n3 weeks. \nLucy’s \nSTAIC \n(State) \nscores showed \na more gradual \nreduction, \nhowever, \nwith her scores eventually \nreaching \na relatively \nlow level within \n5 weeks \n(see Figure \n1)."
  },
  {
    "page": 7,
    "bbox": [
      50.8799934387207,
      446.5621032714844,
      114.00384521484375,
      457.3620910644531
    ],
    "text": "Post-Treatment"
  },
  {
    "page": 7,
    "bbox": [
      50.63999938964844,
      469.3822326660156,
      255.83993530273438,
      622.2680053710938
    ],
    "text": "Mary scored within the average \nrange on the \nvarious \ntests immediately \nfollowing \ntreatment \n(although \nshe continued \nto report \n“a lot” of \nfear, \nher \noverall \nfear \nscore \nwas \nreduced). \nLucy’s scores \nparalleled \nimprovements \nin her \nnighttime \nbehaviors. \nOn \nall \nself-report \nmeasures, \nher scores \nwere within \nthe average \nrange immediately \nfollowing \ntreatment. \nOn the \nAnxiety/Withdrawal \nFactor \nof \nthe \nRBPC, \nMary’s \nrating \nwas reduced \nto within \nthe aver- \nage range, \nwhereas \nLucy’s rating \nwas reduced \nsubstantially \nbut remained \nsomewhat \nelevated \n(see Table \n1)."
  },
  {
    "page": 7,
    "bbox": [
      264.96002197265625,
      69.76207733154297,
      307.4399108886719,
      80.56207275390625
    ],
    "text": "Follow-up"
  },
  {
    "page": 7,
    "bbox": [
      265.2000732421875,
      93.0622329711914,
      470.1602783203125,
      352.74810791015625
    ],
    "text": "The \na-year \nfollow-up \nsession \nwith \nMary \naffirmed \nlong-term \nmaintenance. \nOther \nthan \nsleeping \nin her \nmother’s \nbedroom \non \ntwo \noccasions, \nboth \nduring \nthunderstorms, \nMary \ncontinued \nto sleep \nin her own \nbed \nwithout \ndifficulty. \nShe also \ncontinued \nto experience \nlittle anxiety \nregarding \nsleeping \nin her own bed \naccording \nto her STAIC \n(State) \nscore. \nSimil- \narly, based \non her nighttime \nbehavior \nand re- \nduced level of anxiety \nregarding \nsleeping \nin her \nbed at l-year follow-up, \nthe treatment \ngains for \nLucy \nappeared \nto have \nbeen \nmaintained \nas \nwell. She continued \nto sleep \nin her own bed \nevery \nnight, \nand \nher \nSTAIC \n(State) \nscore \nremained \nlow (see Figure \n1). \nAt two-year \nfollow-up, \nMary’s scores on the \nvarious \npsychological \ntests \nremained \nin the \naverage \nrange, \nas did Lucy’s at l-year \nfollow- \nup. \nMoreover, \nneither \ngirl \nmet \nDSM-III-R \ncriteria \nfor \nseparation \nanxiety \ndisorder \nat \nfollow-up, \nand Lucy no longer \nmet criteria \nfor \nmajor \ndepression."
  },
  {
    "page": 7,
    "bbox": [
      344.1601867675781,
      386.8223571777344,
      383.0401916503906,
      398.3481140136719
    ],
    "text": "Discussion"
  },
  {
    "page": 7,
    "bbox": [
      265.68017578125,
      410.5823669433594,
      470.1602478027344,
      622.5081176757812
    ],
    "text": "The results of these two case studies \nindicate \nthat reinforcement \nfor engaging \nin appropriate \nnighttime \nbehaviors, \nwhen combined \nwith self- \ncontrol \nprocedures, \nwas effective \nin reducing \nnighttime \nfears \nin \nthese \nanxious \ngirls \nex- \nperiencing \nseparation \nanxiety. \nUse \nof \nthe \nmultiple \nbaseline \ndesign \nacross \nsubjects \nand \nthe systematic \ninstitution \nof self-control \ntrain- \ning \nand \nreinforcement \ncontingencies \nin \nan \nadditive \nfashion \nsuggest \nthat \nthe addition \nof \nreinforcement \nwas the \ncritical \nfactor \nin the \nreduction \nof the nighttime \nproblems \nand separ- \nation \nanxieties \nin these two girls. Self-control \ntraining \nin the absence \nof contingent \nreinforce- \nment was only moderately \neffective \nin reducing \nthe girls’ state anxiety. \nFor one child (Mary), \nit \nwas \nnot \nat \nall \neffective \nin \nincreasing \nthe \ntargeted \nbehavior \nof sleeping \nin her own bed,"
  },
  {
    "page": 8,
    "bbox": [
      52.08000183105469,
      51.47801971435547,
      413.3402099609375,
      61.3957633972168
    ],
    "text": "120 \nTIlOMAS \nII. OLLENDICK. \nLOUIS \nP. HAGOPIAN \nand \nROSE \nM. llUN’I%INGER"
  },
  {
    "page": 8,
    "bbox": [
      51.1199951171875,
      68.10208892822266,
      254.8800048828125,
      79.62785339355469
    ],
    "text": "and only slightly \neffective \nfor the other \nchild"
  },
  {
    "page": 8,
    "bbox": [
      50.16007995605469,
      82.0220718383789,
      257.7601623535156,
      539.4679565429688
    ],
    "text": "(Lucy). \nAlthough \nthe girls were not reinforced \nsys- \ntematically \nfor \nsleeping \nin \ntheir \nown \nbeds \nduring \nthe \nself-control \ntraining \nphase. \nthey \nwere praised \nby their parents \nat home \nand by \ntheir therapists \nin the clinic for using the self- \ncontrol \nstrategies \nto assist \nthem \nin doing \nso. \nOnly \nwhen \nthe \nchildren \nwere \nreinforced \ndirectly \nfor \nsleeping \nin their \nown \nbeds \ndid \nsignificant \nbehavior \nchange \noccur. \nOf course, \nwe cannot \nbe sure \nthat \nreinforcement \nalone \nwould \nhave been \neffective \nsince we added \nthe \nreinforcement \ncomponent \nto an ongoing \nself- \ncontrol \nprogram \nand encouraged \nthe continued \nuse of self-control \nstrategies \nthroughout \nthe \nremainder \nof treatment. \nA crossover \ndesign \nwould \nbe necessary \nto disentangle \nthe effects \nand \nto determine \nthe most \nefficacious \ncom- \nponents. \nWhatever \nthe \neffective \ncomponents, \nit is \nclear that the nighttime \nfears of these two girls \nwere reduced \nwith treatment. \nMoreover, \nit is \nevident \nthat \nrelated \nfeatures \ncharacteristic \nof \nseparation \nanxiety \ndisorder \nwere \naddressed \nindirectly. \nTreatment \nof the nighttime \nprob- \nlems \nresulted \nin fewer \nworries \nand concerns \nabout \nharm \nbefalling \nmother \nor fears that she \nwould \nleave \nhome \nand not return. \nMoreover, \nsignificantly \nless \n“clinging” \nbehavior \ntoward \nmother \noccurred \nand \ncomplaints \nof physical \nsymptoms \nwhen \nseparated \nfrom \nmother \nde- \ncreased. \nFinally, \nboth girls were able to spend \ntime away from home with friends \nor at school \nwithout \nmajor \ncomplaints \nof distress. \nIn effect, \nresolution \nof nighttime \nproblems \nserved \nto \nmitigate \na \nvariety \nof \nassociated \nfeatures. \nNeither \ngirl \nmet \nthe \nDSM-III-R \ncriteria \nof \nseparation \nanxiety \ndisorder \nor major \ndepres- \nsion at completion \nof treatment \nor at follow-"
  },
  {
    "page": 8,
    "bbox": [
      50.64009094238281,
      542.1021728515625,
      255.1201629638672,
      621.5479736328125
    ],
    "text": "UP. \nThese \nfindings \nsuggest \nthat nighttime \nfears. \nand \nthe \nnighttime \nbehavioral \nproblems \nthat \naccompany \nthem, \nmay \nbe \nimportant \nand \nadventitious \ntarget \nbehaviors \nin the treatment \nof separation \nanxiety \ndisorder. \nTheir successful \ntreatment \nmay occasion \nchange \nin related \nareas"
  },
  {
    "page": 8,
    "bbox": [
      267.12005615234375,
      68.10221099853516,
      474.0418701171875,
      386.3481140136719
    ],
    "text": "of separation \ndistress \n(i.c.. \nclinging \nto mother, \nstaying \nat a friend’s \nhouse, \nleaving \nfor school, \netc.). \nTheir \nrole \nin \nthe \ndevelopment \nand \nmaintenance \nof separation \nproblems \nremains \nto be explored, \nhowever. \nIt is plausible \nthat \nnormal \nnighttime \nfears \nin \noverly \nsensitive \nchildren \nmay be exacerbated \nand maintained \nby parents \nwho are overly sensitive \nthemselves \nand who go to extreme \nlengths \nto reassure \ntheir \nchildren \nand to shield \nthem from even \nminor \ndiscomfort. \nSuch \n;I process \ncould \nlead \nto \nheightened \nparent-child \ninterdependency, \nrc- \nsulting \nin mutual \nseparation \nconcerns \nthat arc \ncharacteristic \nof \nthese \nchildren \nand \ntheir \nparents. \nSuch \n;I hypothesis \nremains \nto \nbe \nempirically \nevaluated, \nhowever. \nStill. \nit is \nevident \nthat the treatment \nof nighttime \nfears \nand \nparent-child \ninteractions \nsurrounding \nthem \nhad \na salutatory \neffect \non \nthe \nother \nfeatures \nof \nseparation \nanxiety \ndisorder \nin \nthese \ngirls. \nGiven \nthe \nsuccess \nin \ntreating \nnighttime \nfears by Graziano \nand his collcagucs \n(1979. 1980. 19X2), and our demonstration \nthat \ntheir successful \ntreatment \nmay have additional \nsalubrious \neffects. \nthey \nwould \nappear \nto bc \nprime \ntargets \nfor change \nin nighttime \nfearful \nchildren \nwho experience \nseparation \nconcerns."
  },
  {
    "page": 8,
    "bbox": [
      345.8401184082031,
      418.5023498535156,
      385.9199523925781,
      430.0281066894531
    ],
    "text": "Refcrcnccs"
  },
  {
    "page": 9,
    "bbox": [
      147.60000610351562,
      54.271095275878906,
      470.4599304199219,
      63.79572677612305
    ],
    "text": "Cognitive-Behavior \nTherapy \nwith Nighttime \nFearful \nChildren \n121"
  },
  {
    "page": 9,
    "bbox": [
      49.91998291015625,
      71.07108306884766,
      255.6600341796875,
      328.2550048828125
    ],
    "text": "improvement \nat 2% \nto 3%year \nfollow-up. \nJournal \nof \nClinical and Child Psychology, \n50, 598-599. \nGraziano, \nA. M., Mooney, \nK. C., Huber, \nC., & Ignaziak, \nD. (1979). \nSelf-control \ninstructions \nfor children’s \nfear \nreductions. \nJournal of Behavior \nTherupy and Experi- \nmental Psychiatry, 10, 221-227. \nHersen, \nM.. \n& \nBarlow, \nD. \nH. \n(1984). \nSingle \ncase \nexperimental \ndesigns. New York: \nPergamon \nPress. \nHodges, \nK. \n(198.5). \nManual \nfor the child assessment \nschedule. \nDepartment \nof Psychiatry, \nDuke \nUniversity. \nKendall, \nP. \nC.. \n& \nBraswell. \nL. \n(1985). \nCognitive. \nbehavioral therapy for impulsive children: \nNew-‘York: \nGuilford \nPress. \nKing, N. J., Hamilton, \nD. I., & Ollendick, \nT. H. (1988). \nChildren’s phobias: a behavioural perspective. \nChiches- \nter: John \nWiley \n& Sons. \nKovacs, \nM. \n(1978). \nChildren’s \nDepression \nInventory \n(CDI). \nUnpublished \nmanuscript, \nUniversity \nof \nPittsburgh. \nLuria, \nA. R. (1961). \nThe role of speech in the regulation of \nnormal and abnormal behavior. \nNew York: \nLiveright. \nMeichenbaum, \nD. H. (1977). Cognitive-behavior modifica- \ntion. New York: \nPlenum \nPress. \nMorris, \nR. J., \n& Kratochwill. \nT. \nR. \n(1983). \nTreating \nchildren’s fears and phobias: \na behavioural \napproach. \nNew York: \nPergamon \nPress. \nOllendick, \nT. H. (1983). \nReliability \nand validity \nof the \nRevised \nFear Survey \nSchedule \nfor Children \n(FSSC-R). \nBehuviour \nResearch and Therapy, \n21. 685-692."
  },
  {
    "page": 9,
    "bbox": [
      265.679931640625,
      71.0712661743164,
      471.8999328613281,
      275.23602294921875
    ],
    "text": "Ollendick, \nT. H. (1986). \nChild \nand adolescent \nbehavior \ntherapy. \nIn S. L. Garfield, \n& A. E. Bergen \n(Eds.), \nHandbook \nof psychotherapy \nand behavior change (3rd \nEd.). \npp. \n525-564. \nNew York: \nJohn \nWiley \n& Sons. \nOllendick. \nT. \nH., \n& Francis, \nG. \n(1988). \nBehavioral \nassessment \nand treatment \nof childhood \nphobias. \nBehavi- \noral Modification, \n12. 165-204. \nOllendick, \nT. \nH.. \n& \nHuntzinger, \nR. \nM. \n(1991). \nSeparation \nanxiety \ndisorders \nin children. \nIn M. Hersen \n& C. G. \nLast \n(Eds.). \nHandbook \nof child and adult \npsychopathology: \nA longitudinal perspective. \npp. \n133- \n149. New York: \nPergamon \nPress. \nQuay, \nH. C., & Peterson, \nD. R. (1983). \nManual for the \nRevised \nBehavior \nProblem \nChecklist. \nUnpublished \nmanuscript. \nReynolds. \nC. R., \n& Richmond, \nB. 0. \n(1978). \n“What \nI \nthink \nand \nfeel”: \nA \nrevised \nmeasure \nof \nchildren’s \nmanifest \nanxiety. \nJournal of Abnormal \nChild Psychol- \nogy, 6, 271-280. \nRichards, \nC. \nS., \n& Siegel, \nL. J. \n(1978). \nBehavioral \ntreatment \nof anxiety \nstates \nand avoidance \nbehaviors \nin \nchildren. \nIn D. Macholin \n(Ed.), \nChild behavior therapy, \npp. 274-338. \nNew York: \nGardner \nPress. \n. ."
  },
  {
    "page": 9,
    "bbox": [
      265.43988037109375,
      274.8313903808594,
      471.17987060546875,
      328.75604248046875
    ],
    "text": "Silverman. \nW. K.. & Nelles. \nW. B. (1988). \nThe Anxietv \nDisorders \nInterview \nSchedule \nfor Children. \nJournal of \nChild and Adolescent \nPsychiatry, 27, 772-778.. \nSpielberger, \nC. \nD. \n(1973). \nManual for \nthe State-Trait \nAnxiety Inventory for Children. Palo Alto, CA: Consult- \ning Psychologists \nPress."
  }
]